<?xml version="1.0" encoding="UTF-8" standalone="yes"?>
<groupmgt>
	<group name="AutomationAccessAreaGroup" type="RAT_VEND_HIER321">
		<group-element>
			<key value="1" name="RAT" />
			<key value="ERICSSON" name="VENDOR" />
			<key value="smartone_R:RNC09:RNC09" name="HIERARCHY_3" />
			<key value="82197D" name="HIERARCHY_1" />
		</group-element>
		<group-element>
			<key value="1" name="RAT" />
			<key value="ERICSSON" name="VENDOR" />
			<key value="smartone_R:RNC09:RNC09" name="HIERARCHY_3" />
			<key value="84162F" name="HIERARCHY_1" />
		</group-element>
		<group-element>
			<key value="1" name="RAT" />
			<key value="ERICSSON" name="VENDOR" />
			<key value="smartone_R:RNC09:RNC09" name="HIERARCHY_3" />
			<key value="84342H" name="HIERARCHY_1" />
		</group-element>
		<group-element>
			<key value="1" name="RAT" />
			<key value="ERICSSON" name="VENDOR" />
			<key value="smartone_R:RNC09:RNC09" name="HIERARCHY_3" />
			<key value="86053A" name="HIERARCHY_1" />
		</group-element>
		<group-element>
			<key value="1" name="RAT" />
			<key value="ERICSSON" name="VENDOR" />
			<key value="smartone_R:RNC09:RNC09" name="HIERARCHY_3" />
			<key value="82013S" name="HIERARCHY_1" />
		</group-element>
		<group-element>
			<key value="1" name="RAT" />
			<key value="ERICSSON" name="VENDOR" />
			<key value="smartone_R:RNC09:RNC09" name="HIERARCHY_3" />
			<key value="84675K" name="HIERARCHY_1" />
		</group-element>
		<group-element>
			<key value="1" name="RAT" />
			<key value="ERICSSON" name="VENDOR" />
			<key value="smartone_R:RNC09:RNC09" name="HIERARCHY_3" />
			<key value="82040A" name="HIERARCHY_1" />
		</group-element>
		<group-element>
			<key value="1" name="RAT" />
			<key value="ERICSSON" name="VENDOR" />
			<key value="smartone_R:RNC09:RNC09" name="HIERARCHY_3" />
			<key value="13581" name="HIERARCHY_1" />
		</group-element>
		<group-element>
			<key value="1" name="RAT" />
			<key value="ERICSSON" name="VENDOR" />
			<key value="smartone_R:RNC09:RNC09" name="HIERARCHY_3" />
			<key value="81626A" name="HIERARCHY_1" />
		</group-element>
		<group-element>
			<key value="1" name="RAT" />
			<key value="ERICSSON" name="VENDOR" />
			<key value="smartone_R:RNC09:RNC09" name="HIERARCHY_3" />
			<key value="18151" name="HIERARCHY_1" />
		</group-element>
		<group-element>
			<key value="1" name="RAT" />
			<key value="ERICSSON" name="VENDOR" />
			<key value="smartone_R:RNC09:RNC09" name="HIERARCHY_3" />
			<key value="18152" name="HIERARCHY_1" />
		</group-element>
		<group-element>
			<key value="1" name="RAT" />
			<key value="ERICSSON" name="VENDOR" />
			<key value="smartone_R:RNC09:RNC09" name="HIERARCHY_3" />
			<key value="18153" name="HIERARCHY_1" />
		</group-element>
		<group-element>
			<key value="1" name="RAT" />
			<key value="ERICSSON" name="VENDOR" />
			<key value="smartone_R:RNC09:RNC09" name="HIERARCHY_3" />
			<key value="12881" name="HIERARCHY_1" />
		</group-element>
	</group>
</groupmgt>